quit/__init__.py
quit/application.py
quit/cache.py
quit/conf.py
quit/core.py
quit/echo.py
quit/exceptions.py
quit/git.py
quit/graphs.py
quit/helpers.py
quit/merge.py
quit/namespace.py
quit/provenance.py
quit/run.py
quit/utils.py
quit/plugins/__init__.py
quit/plugins/serializers/__init__.py
quit/plugins/serializers/results/__init__.py
quit/plugins/serializers/results/htmlresults.py
quit/tools/__init__.py
quit/tools/algebra.py
quit/tools/evaluate.py
quit/tools/processor.py
quit/tools/update.py
quit/web/__init__.py
quit/web/app.py
quit/web/service.py
quit/web/extras/__init__.py
quit/web/extras/commits_graph.py
quit/web/modules/__init__.py
quit/web/modules/application.py
quit/web/modules/debug.py
quit/web/modules/endpoint.py
quit/web/modules/git.py
quit/web/static/css/bootstrap-theme.min.css
quit/web/static/css/bootstrap.min.css
quit/web/static/css/bootstrap.min.css.map
quit/web/static/css/codemirror.css
quit/web/static/css/font-awesome.min.css
quit/web/static/css/quit.css
quit/web/static/css/yasqe.min.css
quit/web/static/css/yasr.min.css
quit/web/static/fonts/FontAwesome.otf
quit/web/static/fonts/fontawesome-webfont.eot
quit/web/static/fonts/fontawesome-webfont.svg
quit/web/static/fonts/fontawesome-webfont.ttf
quit/web/static/fonts/fontawesome-webfont.woff
quit/web/static/fonts/fontawesome-webfont.woff2
quit/web/static/fonts/glyphicons-halflings-regular.eot
quit/web/static/fonts/glyphicons-halflings-regular.svg
quit/web/static/fonts/glyphicons-halflings-regular.ttf
quit/web/static/fonts/glyphicons-halflings-regular.woff
quit/web/static/fonts/glyphicons-halflings-regular.woff2
quit/web/static/fonts/roboto-condensed-v14-latin-regular.eot
quit/web/static/fonts/roboto-condensed-v14-latin-regular.svg
quit/web/static/fonts/roboto-condensed-v14-latin-regular.ttf
quit/web/static/fonts/roboto-condensed-v14-latin-regular.woff
quit/web/static/fonts/roboto-condensed-v14-latin-regular.woff2
quit/web/static/js/bootstrap.min.js
quit/web/static/js/jquery-3.2.1.min.js
quit_store-0.24.0.dist-info/LICENSE
quit_store-0.24.0.dist-info/METADATA
quit_store-0.24.0.dist-info/WHEEL
quit_store-0.24.0.dist-info/entry_points.txt
quit_store-0.24.0.dist-info/top_level.txt
quit_store-0.24.0.dist-info/RECORD
